{
  "_comment": "Generated by tools/bump_clock_pin.py from PINT. Schema only; the bulk .clk/.dat are downloaded at runtime.",
  "format_by_extension": {
    ".dat": "tempo",
    ".clk": "tempo2"
  },
  "default_bipm": "BIPM2023",
  "bipm_bogus_through": "bipm2019",
  "files": {
    "eff2gps.clk": {
      "format": "tempo2",
      "bogus_last_correction": true,
      "valid_beyond_ends": false
    },
    "effix2gps.clk": {
      "format": "tempo2",
      "bogus_last_correction": false,
      "valid_beyond_ends": false
    },
    "gps2utc.clk": {
      "format": "tempo2",
      "bogus_last_correction": false,
      "valid_beyond_ends": false
    },
    "jb2gps.clk": {
      "format": "tempo2",
      "bogus_last_correction": true,
      "valid_beyond_ends": false
    },
    "jbdfb2jb.clk": {
      "format": "tempo2",
      "bogus_last_correction": true,
      "valid_beyond_ends": true
    },
    "jbroach2jb.clk": {
      "format": "tempo2",
      "bogus_last_correction": true,
      "valid_beyond_ends": true
    },
    "leap2effix.clk": {
      "format": "tempo2",
      "bogus_last_correction": true,
      "valid_beyond_ends": false
    },
    "mk2utc_observatory.clk": {
      "format": "tempo2",
      "bogus_last_correction": false,
      "valid_beyond_ends": false
    },
    "mo2gps.clk": {
      "format": "tempo2",
      "bogus_last_correction": true,
      "valid_beyond_ends": false
    },
    "ncyobs2obspm.clk": {
      "format": "tempo2",
      "bogus_last_correction": true,
      "valid_beyond_ends": false
    },
    "obspm2gps.clk": {
      "format": "tempo2",
      "bogus_last_correction": true,
      "valid_beyond_ends": false
    },
    "pks2gps.clk": {
      "format": "tempo2",
      "bogus_last_correction": false,
      "valid_beyond_ends": false
    },
    "tai2tt_bipm2023.clk": {
      "format": "tempo2",
      "bogus_last_correction": false,
      "valid_beyond_ends": false
    },
    "time_ao.dat": {
      "format": "tempo",
      "bogus_last_correction": false,
      "valid_beyond_ends": false
    },
    "time_fast.dat": {
      "format": "tempo",
      "bogus_last_correction": false,
      "valid_beyond_ends": false
    },
    "time_gb140.dat": {
      "format": "tempo",
      "bogus_last_correction": false,
      "valid_beyond_ends": false
    },
    "time_gb853.dat": {
      "format": "tempo",
      "bogus_last_correction": true,
      "valid_beyond_ends": false
    },
    "time_gbt.dat": {
      "format": "tempo",
      "bogus_last_correction": false,
      "valid_beyond_ends": false
    },
    "time_vla.dat": {
      "format": "tempo",
      "bogus_last_correction": false,
      "valid_beyond_ends": false
    },
    "wsrt2gps.clk": {
      "format": "tempo2",
      "bogus_last_correction": false,
      "valid_beyond_ends": false
    }
  },
  "observatories": {
    "acre": {
      "clock_file": [],
      "apply_gps2utc": true,
      "timescale": "utc",
      "itrf_xyz": [
        3573741.1,
        -269156.74,
        5258407.3
      ],
      "aliases": [
        "a",
        "acreroad",
        "ar"
      ],
      "tempo_code": null,
      "itoa_code": null
    },
    "algonquin": {
      "clock_file": [],
      "apply_gps2utc": true,
      "timescale": "utc",
      "itrf_xyz": [
        918091.6472072796,
        -4346129.702203057,
        4562012.861165226
      ],
      "aliases": [
        "ar",
        "aro"
      ],
      "tempo_code": null,
      "itoa_code": "ar"
    },
    "arecibo": {
      "clock_file": [
        "time_ao.dat"
      ],
      "apply_gps2utc": true,
      "timescale": "utc",
      "itrf_xyz": [
        2390487.08,
        -5564731.357,
        1994720.633
      ],
      "aliases": [
        "3",
        "aoutc",
        "ao"
      ],
      "tempo_code": "3",
      "itoa_code": "ao"
    },
    "arecibo_pre_2021": {
      "clock_file": [
        "time_ao.dat"
      ],
      "apply_gps2utc": true,
      "timescale": "utc",
      "itrf_xyz": [
        2390490.0,
        -5564764.0,
        1994727.0
      ],
      "aliases": [],
      "tempo_code": null,
      "itoa_code": null
    },
    "ata": {
      "clock_file": [],
      "apply_gps2utc": true,
      "timescale": "utc",
      "itrf_xyz": [
        -2524263.18,
        -4123529.78,
        4147966.36
      ],
      "aliases": [
        "hcro"
      ],
      "tempo_code": null,
      "itoa_code": null
    },
    "axis": {
      "clock_file": [],
      "apply_gps2utc": false,
      "timescale": "utc",
      "itrf_xyz": [
        6378138.0,
        0.0,
        0.0
      ],
      "aliases": [
        "axi"
      ],
      "tempo_code": null,
      "itoa_code": null
    },
    "barycenter": {
      "clock_file": [],
      "apply_gps2utc": false,
      "timescale": "tdb",
      "itrf_xyz": null,
      "aliases": [
        "bary",
        "bat",
        "@",
        "ssb"
      ],
      "tempo_code": null,
      "itoa_code": null
    },
    "cambridge": {
      "clock_file": [],
      "apply_gps2utc": true,
      "timescale": "utc",
      "itrf_xyz": [
        3919982.752,
        2651.982,
        5013849.826
      ],
      "aliases": [
        "cam"
      ],
      "tempo_code": null,
      "itoa_code": null
    },
    "ccera": {
      "clock_file": [],
      "apply_gps2utc": true,
      "timescale": "utc",
      "itrf_xyz": [
        1081906.02007569,
        -4358005.62381148,
        4514986.16069416
      ],
      "aliases": [],
      "tempo_code": null,
      "itoa_code": null
    },
    "chime": {
      "clock_file": [],
      "apply_gps2utc": true,
      "timescale": "utc",
      "itrf_xyz": [
        -2059166.313,
        -3621302.972,
        4814304.113
      ],
      "aliases": [
        "ch",
        "y"
      ],
      "tempo_code": "y",
      "itoa_code": "ch"
    },
    "darnhall": {
      "clock_file": [],
      "apply_gps2utc": true,
      "timescale": "utc",
      "itrf_xyz": [
        3828714.504,
        -169458.987,
        5080647.749
      ],
      "aliases": [],
      "tempo_code": null,
      "itoa_code": null
    },
    "de601": {
      "clock_file": [],
      "apply_gps2utc": true,
      "timescale": "utc",
      "itrf_xyz": [
        4034101.901,
        487012.401,
        4900230.21
      ],
      "aliases": [
        "eflfr"
      ],
      "tempo_code": null,
      "itoa_code": null
    },
    "de601hba": {
      "clock_file": [],
      "apply_gps2utc": true,
      "timescale": "utc",
      "itrf_xyz": [
        4034101.901,
        487012.401,
        4900230.21
      ],
      "aliases": [
        "eflfrhba"
      ],
      "tempo_code": null,
      "itoa_code": null
    },
    "de601lba": {
      "clock_file": [],
      "apply_gps2utc": true,
      "timescale": "utc",
      "itrf_xyz": [
        4034038.635,
        487026.223,
        4900280.057
      ],
      "aliases": [
        "eflfrlba"
      ],
      "tempo_code": null,
      "itoa_code": null
    },
    "de601lbh": {
      "clock_file": [],
      "apply_gps2utc": true,
      "timescale": "utc",
      "itrf_xyz": [
        4034038.635,
        487026.223,
        4900280.057
      ],
      "aliases": [
        "eflfrlbh"
      ],
      "tempo_code": null,
      "itoa_code": null
    },
    "de602": {
      "clock_file": [],
      "apply_gps2utc": true,
      "timescale": "utc",
      "itrf_xyz": [
        4152568.416,
        828788.802,
        4754361.926
      ],
      "aliases": [
        "uwlfr"
      ],
      "tempo_code": null,
      "itoa_code": null
    },
    "de602hba": {
      "clock_file": [],
      "apply_gps2utc": true,
      "timescale": "utc",
      "itrf_xyz": [
        4152568.416,
        828788.802,
        4754361.926
      ],
      "aliases": [
        "uwlfrhba"
      ],
      "tempo_code": null,
      "itoa_code": null
    },
    "de602lba": {
      "clock_file": [],
      "apply_gps2utc": true,
      "timescale": "utc",
      "itrf_xyz": [
        4152561.068,
        828868.725,
        4754356.878
      ],
      "aliases": [
        "uwlfrlba"
      ],
      "tempo_code": null,
      "itoa_code": null
    },
    "de602lbh": {
      "clock_file": [],
      "apply_gps2utc": true,
      "timescale": "utc",
      "itrf_xyz": [
        4152561.068,
        828868.725,
        4754356.878
      ],
      "aliases": [
        "uwlfrlbh"
      ],
      "tempo_code": null,
      "itoa_code": null
    },
    "de603": {
      "clock_file": [],
      "apply_gps2utc": true,
      "timescale": "utc",
      "itrf_xyz": [
        3940296.126,
        816722.532,
        4932394.152
      ],
      "aliases": [
        "tblfr"
      ],
      "tempo_code": null,
      "itoa_code": null
    },
    "de603hba": {
      "clock_file": [],
      "apply_gps2utc": true,
      "timescale": "utc",
      "itrf_xyz": [
        3940296.126,
        816722.532,
        4932394.152
      ],
      "aliases": [
        "tblfrhba"
      ],
      "tempo_code": null,
      "itoa_code": null
    },
    "de603lba": {
      "clock_file": [],
      "apply_gps2utc": true,
      "timescale": "utc",
      "itrf_xyz": [
        3940285.328,
        816802.001,
        4932392.757
      ],
      "aliases": [
        "tblfrlba"
      ],
      "tempo_code": null,
      "itoa_code": null
    },
    "de603lbh": {
      "clock_file": [],
      "apply_gps2utc": true,
      "timescale": "utc",
      "itrf_xyz": [
        3940285.328,
        816802.001,
        4932392.757
      ],
      "aliases": [
        "tblfrlbh"
      ],
      "tempo_code": null,
      "itoa_code": null
    },
    "de604": {
      "clock_file": [],
      "apply_gps2utc": true,
      "timescale": "utc",
      "itrf_xyz": [
        3796380.254,
        877613.809,
        5032712.272
      ],
      "aliases": [
        "polfr"
      ],
      "tempo_code": null,
      "itoa_code": null
    },
    "de604hba": {
      "clock_file": [],
      "apply_gps2utc": true,
      "timescale": "utc",
      "itrf_xyz": [
        3796380.254,
        877613.809,
        5032712.272
      ],
      "aliases": [
        "polfrhba"
      ],
      "tempo_code": null,
      "itoa_code": null
    },
    "de604lba": {
      "clock_file": [],
      "apply_gps2utc": true,
      "timescale": "utc",
      "itrf_xyz": [
        3796327.609,
        877591.315,
        5032757.252
      ],
      "aliases": [
        "polfrlba"
      ],
      "tempo_code": null,
      "itoa_code": null
    },
    "de604lbh": {
      "clock_file": [],
      "apply_gps2utc": true,
      "timescale": "utc",
      "itrf_xyz": [
        3796327.609,
        877591.315,
        5032757.252
      ],
      "aliases": [
        "polfrlbh"
      ],
      "tempo_code": null,
      "itoa_code": null
    },
    "de605": {
      "clock_file": [],
      "apply_gps2utc": true,
      "timescale": "utc",
      "itrf_xyz": [
        4005681.407,
        450968.304,
        4926457.94
      ],
      "aliases": [
        "julfr"
      ],
      "tempo_code": null,
      "itoa_code": null
    },
    "de605hba": {
      "clock_file": [],
      "apply_gps2utc": true,
      "timescale": "utc",
      "itrf_xyz": [
        4005681.407,
        450968.304,
        4926457.94
      ],
      "aliases": [
        "julfrhba"
      ],
      "tempo_code": null,
      "itoa_code": null
    },
    "de605lba": {
      "clock_file": [],
      "apply_gps2utc": true,
      "timescale": "utc",
      "itrf_xyz": [
        4005681.742,
        450968.282,
        4926457.67
      ],
      "aliases": [
        "julfrlba"
      ],
      "tempo_code": null,
      "itoa_code": null
    },
    "de605lbh": {
      "clock_file": [],
      "apply_gps2utc": true,
      "timescale": "utc",
      "itrf_xyz": [
        4005681.742,
        450968.282,
        4926457.67
      ],
      "aliases": [
        "julfrlbh"
      ],
      "tempo_code": null,
      "itoa_code": null
    },
    "de609": {
      "clock_file": [],
      "apply_gps2utc": true,
      "timescale": "utc",
      "itrf_xyz": [
        3727218.128,
        655108.821,
        5117002.847
      ],
      "aliases": [
        "ndlfr"
      ],
      "tempo_code": null,
      "itoa_code": null
    },
    "de609hba": {
      "clock_file": [],
      "apply_gps2utc": true,
      "timescale": "utc",
      "itrf_xyz": [
        3727218.128,
        655108.821,
        5117002.847
      ],
      "aliases": [
        "ndlfrhba"
      ],
      "tempo_code": null,
      "itoa_code": null
    },
    "de609lba": {
      "clock_file": [],
      "apply_gps2utc": true,
      "timescale": "utc",
      "itrf_xyz": [
        3727207.778,
        655184.9,
        5117000.625
      ],
      "aliases": [
        "ndlfrlba"
      ],
      "tempo_code": null,
      "itoa_code": null
    },
    "de609lbh": {
      "clock_file": [],
      "apply_gps2utc": true,
      "timescale": "utc",
      "itrf_xyz": [
        3727207.778,
        655184.9,
        5117000.625
      ],
      "aliases": [
        "ndlfrlbh"
      ],
      "tempo_code": null,
      "itoa_code": null
    },
    "defford": {
      "clock_file": [],
      "apply_gps2utc": true,
      "timescale": "utc",
      "itrf_xyz": [
        3923069.135,
        -146804.404,
        5009320.57
      ],
      "aliases": [],
      "tempo_code": null,
      "itoa_code": null
    },
    "drao": {
      "clock_file": [],
      "apply_gps2utc": true,
      "timescale": "utc",
      "itrf_xyz": [
        -2058897.5725006417,
        -3621371.264826613,
        4814353.577678314
      ],
      "aliases": [
        "dr"
      ],
      "tempo_code": null,
      "itoa_code": "dr"
    },
    "dss_43": {
      "clock_file": [],
      "apply_gps2utc": true,
      "timescale": "utc",
      "itrf_xyz": [
        -4460892.6,
        2682358.9,
        -3674756.0
      ],
      "aliases": [
        "tid43"
      ],
      "tempo_code": null,
      "itoa_code": null
    },
    "effelsberg": {
      "clock_file": [
        "eff2gps.clk"
      ],
      "apply_gps2utc": true,
      "timescale": "utc",
      "itrf_xyz": [
        4033947.146,
        486990.898,
        4900431.067
      ],
      "aliases": [
        "ef",
        "g",
        "eff"
      ],
      "tempo_code": "g",
      "itoa_code": "ef"
    },
    "effelsberg_asterix": {
      "clock_file": [
        "effix2gps.clk"
      ],
      "apply_gps2utc": true,
      "timescale": "utc",
      "itrf_xyz": [
        4033949.5,
        486989.4,
        4900430.8
      ],
      "aliases": [
        "effix"
      ],
      "tempo_code": null,
      "itoa_code": null
    },
    "effelsberg_pre_2021": {
      "clock_file": [
        "eff2gps.clk"
      ],
      "apply_gps2utc": true,
      "timescale": "utc",
      "itrf_xyz": [
        4033949.5,
        486989.4,
        4900430.8
      ],
      "aliases": [],
      "tempo_code": null,
      "itoa_code": null
    },
    "fast": {
      "clock_file": [
        "time_fast.dat"
      ],
      "apply_gps2utc": true,
      "timescale": "utc",
      "itrf_xyz": [
        -1668557.0,
        5506838.0,
        2744934.0
      ],
      "aliases": [
        "k",
        "fa"
      ],
      "tempo_code": "k",
      "itoa_code": "fa"
    },
    "fi609": {
      "clock_file": [],
      "apply_gps2utc": true,
      "timescale": "utc",
      "itrf_xyz": [
        2136819.194,
        810039.5757,
        5935299.0536
      ],
      "aliases": [
        "filfr"
      ],
      "tempo_code": null,
      "itoa_code": null
    },
    "fi609hba": {
      "clock_file": [],
      "apply_gps2utc": true,
      "timescale": "utc",
      "itrf_xyz": [
        2136819.194,
        810039.5757,
        5935299.0536
      ],
      "aliases": [
        "filfrhba"
      ],
      "tempo_code": null,
      "itoa_code": null
    },
    "fi609lba": {
      "clock_file": [],
      "apply_gps2utc": true,
      "timescale": "utc",
      "itrf_xyz": [
        2136833.225,
        810088.74,
        5935285.279
      ],
      "aliases": [
        "filfrlba"
      ],
      "tempo_code": null,
      "itoa_code": null
    },
    "fi609lbh": {
      "clock_file": [],
      "apply_gps2utc": true,
      "timescale": "utc",
      "itrf_xyz": [
        2136833.225,
        810088.74,
        5935285.279
      ],
      "aliases": [
        "filfrlbh"
      ],
      "tempo_code": null,
      "itoa_code": null
    },
    "fr606": {
      "clock_file": [],
      "apply_gps2utc": true,
      "timescale": "utc",
      "itrf_xyz": [
        4324017.054,
        165545.16,
        4670271.072
      ],
      "aliases": [
        "frlfr"
      ],
      "tempo_code": null,
      "itoa_code": null
    },
    "fr606hba": {
      "clock_file": [],
      "apply_gps2utc": true,
      "timescale": "utc",
      "itrf_xyz": [
        4324017.054,
        165545.16,
        4670271.072
      ],
      "aliases": [
        "frlfrhba"
      ],
      "tempo_code": null,
      "itoa_code": null
    },
    "fr606lba": {
      "clock_file": [],
      "apply_gps2utc": true,
      "timescale": "utc",
      "itrf_xyz": [
        4323980.155,
        165608.408,
        4670302.803
      ],
      "aliases": [
        "frlfrlba"
      ],
      "tempo_code": null,
      "itoa_code": null
    },
    "fr606lbh": {
      "clock_file": [],
      "apply_gps2utc": true,
      "timescale": "utc",
      "itrf_xyz": [
        4323980.155,
        165608.408,
        4670302.803
      ],
      "aliases": [
        "frlfrlbh"
      ],
      "tempo_code": null,
      "itoa_code": null
    },
    "gb140": {
      "clock_file": [
        "time_gb140.dat"
      ],
      "apply_gps2utc": true,
      "timescale": "utc",
      "itrf_xyz": [
        882872.57,
        -4924552.73,
        3944154.92
      ],
      "aliases": [
        "g1",
        "a"
      ],
      "tempo_code": "a",
      "itoa_code": "g1"
    },
    "gb300": {
      "clock_file": [],
      "apply_gps2utc": true,
      "timescale": "utc",
      "itrf_xyz": [
        881856.58,
        -4925311.86,
        3943459.7
      ],
      "aliases": [
        "9",
        "g3"
      ],
      "tempo_code": "9",
      "itoa_code": "g3"
    },
    "gb853": {
      "clock_file": [
        "time_gb853.dat"
      ],
      "apply_gps2utc": true,
      "timescale": "utc",
      "itrf_xyz": [
        882315.33,
        -4925191.41,
        3943414.05
      ],
      "aliases": [
        "b",
        "g8"
      ],
      "tempo_code": "b",
      "itoa_code": "g8"
    },
    "gb_20m_xyz": {
      "clock_file": [],
      "apply_gps2utc": true,
      "timescale": "utc",
      "itrf_xyz": [
        883772.7974,
        -4924385.5975,
        3944042.4991
      ],
      "aliases": [
        "g2"
      ],
      "tempo_code": null,
      "itoa_code": "g2"
    },
    "gbt": {
      "clock_file": [
        "time_gbt.dat"
      ],
      "apply_gps2utc": true,
      "timescale": "utc",
      "itrf_xyz": [
        882589.289,
        -4924872.368,
        3943729.418
      ],
      "aliases": [
        "gb",
        "1"
      ],
      "tempo_code": "1",
      "itoa_code": "gb"
    },
    "gbt_pre_2021": {
      "clock_file": [
        "time_gbt.dat"
      ],
      "apply_gps2utc": true,
      "timescale": "utc",
      "itrf_xyz": [
        882589.65,
        -4924872.32,
        3943729.348
      ],
      "aliases": [],
      "tempo_code": null,
      "itoa_code": null
    },
    "geo600": {
      "clock_file": [],
      "apply_gps2utc": true,
      "timescale": "utc",
      "itrf_xyz": [
        3856309.9493,
        666598.9563,
        5019641.4172
      ],
      "aliases": [
        "geohf"
      ],
      "tempo_code": null,
      "itoa_code": null
    },
    "geocenter": {
      "clock_file": [],
      "apply_gps2utc": false,
      "timescale": "utc",
      "itrf_xyz": [
        0.0,
        0.0,
        0.0
      ],
      "aliases": [
        "geo_nogps",
        "0",
        "geo",
        "coe",
        "o"
      ],
      "tempo_code": null,
      "itoa_code": null
    },
    "geocenter_gps": {
      "clock_file": [],
      "apply_gps2utc": true,
      "timescale": "utc",
      "itrf_xyz": [
        0.0,
        0.0,
        0.0
      ],
      "aliases": [
        "geo_gps",
        "coe_gps"
      ],
      "tempo_code": null,
      "itoa_code": null
    },
    "gmrt": {
      "clock_file": [],
      "apply_gps2utc": true,
      "timescale": "utc",
      "itrf_xyz": [
        1656342.3,
        5797947.77,
        2073243.16
      ],
      "aliases": [
        "gm",
        "r"
      ],
      "tempo_code": "r",
      "itoa_code": "gm"
    },
    "goldstone": {
      "clock_file": [],
      "apply_gps2utc": true,
      "timescale": "utc",
      "itrf_xyz": [
        -2353621.22,
        -4641341.52,
        3677052.352
      ],
      "aliases": [
        "gs"
      ],
      "tempo_code": null,
      "itoa_code": null
    },
    "grao": {
      "clock_file": [],
      "apply_gps2utc": true,
      "timescale": "utc",
      "itrf_xyz": [
        6346273.531,
        -33779.7127,
        634844.9454
      ],
      "aliases": [
        "grao"
      ],
      "tempo_code": null,
      "itoa_code": null
    },
    "hamburg": {
      "clock_file": [],
      "apply_gps2utc": true,
      "timescale": "utc",
      "itrf_xyz": [
        3788815.62,
        1131748.336,
        5035101.19
      ],
      "aliases": [],
      "tempo_code": null,
      "itoa_code": null
    },
    "hartebeesthoek": {
      "clock_file": [],
      "apply_gps2utc": true,
      "timescale": "utc",
      "itrf_xyz": [
        5085442.78,
        2668263.483,
        -2768697.034
      ],
      "aliases": [
        "hart"
      ],
      "tempo_code": null,
      "itoa_code": null
    },
    "hawc": {
      "clock_file": [],
      "apply_gps2utc": true,
      "timescale": "utc",
      "itrf_xyz": [
        -767864.42219771,
        -5987810.65796205,
        2064148.57332404
      ],
      "aliases": [],
      "tempo_code": null,
      "itoa_code": null
    },
    "hess": {
      "clock_file": [],
      "apply_gps2utc": true,
      "timescale": "utc",
      "itrf_xyz": [
        5622462.3793,
        1665449.2317,
        -2505096.8054
      ],
      "aliases": [],
      "tempo_code": null,
      "itoa_code": null
    },
    "hobart": {
      "clock_file": [],
      "apply_gps2utc": true,
      "timescale": "utc",
      "itrf_xyz": [
        -3950077.96,
        2522377.31,
        -4311667.52
      ],
      "aliases": [
        "4",
        "ho"
      ],
      "tempo_code": "4",
      "itoa_code": "ho"
    },
    "iar1": {
      "clock_file": [],
      "apply_gps2utc": true,
      "timescale": "utc",
      "itrf_xyz": [
        2765357.08,
        -4449628.98,
        -3625726.47
      ],
      "aliases": [],
      "tempo_code": null,
      "itoa_code": null
    },
    "iar2": {
      "clock_file": [],
      "apply_gps2utc": true,
      "timescale": "utc",
      "itrf_xyz": [
        2765322.49,
        -4449569.52,
        -3625825.14
      ],
      "aliases": [],
      "tempo_code": null,
      "itoa_code": null
    },
    "jb_42ft": {
      "clock_file": [],
      "apply_gps2utc": true,
      "timescale": "utc",
      "itrf_xyz": [
        3822294.825,
        -153862.275,
        5085987.071
      ],
      "aliases": [
        "jb42"
      ],
      "tempo_code": null,
      "itoa_code": null
    },
    "jb_mkii": {
      "clock_file": [],
      "apply_gps2utc": true,
      "timescale": "utc",
      "itrf_xyz": [
        3822846.76,
        -153802.28,
        5086285.9
      ],
      "aliases": [
        "jbmk2",
        "h",
        "j2"
      ],
      "tempo_code": "h",
      "itoa_code": "j2"
    },
    "jb_mkii_dfb": {
      "clock_file": [],
      "apply_gps2utc": true,
      "timescale": "utc",
      "itrf_xyz": [
        3822846.76,
        -153802.28,
        5086285.9
      ],
      "aliases": [
        "jbmk2dfb"
      ],
      "tempo_code": null,
      "itoa_code": null
    },
    "jb_mkii_rch": {
      "clock_file": [],
      "apply_gps2utc": true,
      "timescale": "utc",
      "itrf_xyz": [
        3822846.76,
        -153802.28,
        5086285.9
      ],
      "aliases": [
        "jbmk2roach"
      ],
      "tempo_code": null,
      "itoa_code": null
    },
    "jbafb": {
      "clock_file": [],
      "apply_gps2utc": true,
      "timescale": "utc",
      "itrf_xyz": [
        3822625.769,
        -154105.255,
        5086486.256
      ],
      "aliases": [
        "jboafb"
      ],
      "tempo_code": null,
      "itoa_code": null
    },
    "jbdfb": {
      "clock_file": [
        "jbdfb2jb.clk",
        "jb2gps.clk"
      ],
      "apply_gps2utc": true,
      "timescale": "utc",
      "itrf_xyz": [
        3822625.769,
        -154105.255,
        5086486.256
      ],
      "aliases": [
        "jbodfb"
      ],
      "tempo_code": null,
      "itoa_code": null
    },
    "jbroach": {
      "clock_file": [
        "jbroach2jb.clk",
        "jb2gps.clk"
      ],
      "apply_gps2utc": true,
      "timescale": "utc",
      "itrf_xyz": [
        3822625.769,
        -154105.255,
        5086486.256
      ],
      "aliases": [
        "jboroach"
      ],
      "tempo_code": null,
      "itoa_code": null
    },
    "jodrell": {
      "clock_file": [
        "jb2gps.clk"
      ],
      "apply_gps2utc": true,
      "timescale": "utc",
      "itrf_xyz": [
        3822625.769,
        -154105.255,
        5086486.256
      ],
      "aliases": [
        "jb",
        "8"
      ],
      "tempo_code": "8",
      "itoa_code": "jb"
    },
    "jodrell_pre_2021": {
      "clock_file": [
        "jb2gps.clk"
      ],
      "apply_gps2utc": true,
      "timescale": "utc",
      "itrf_xyz": [
        3822626.04,
        -154105.65,
        5086486.04
      ],
      "aliases": [],
      "tempo_code": null,
      "itoa_code": null
    },
    "jodrellm4": {
      "clock_file": [],
      "apply_gps2utc": true,
      "timescale": "utc",
      "itrf_xyz": [
        3822252.643,
        -153995.683,
        5086051.443
      ],
      "aliases": [
        "jbm4"
      ],
      "tempo_code": null,
      "itoa_code": null
    },
    "kagra": {
      "clock_file": [],
      "apply_gps2utc": true,
      "timescale": "utc",
      "itrf_xyz": [
        -3777336.024,
        3484898.411,
        3765313.697
      ],
      "aliases": [
        "lcgt",
        "k1"
      ],
      "tempo_code": null,
      "itoa_code": null
    },
    "kat-7": {
      "clock_file": [],
      "apply_gps2utc": true,
      "timescale": "utc",
      "itrf_xyz": [
        5109943.105,
        2003650.7359,
        -3239908.3195
      ],
      "aliases": [
        "k7"
      ],
      "tempo_code": null,
      "itoa_code": null
    },
    "knockin": {
      "clock_file": [],
      "apply_gps2utc": true,
      "timescale": "utc",
      "itrf_xyz": [
        3859711.492,
        -201995.082,
        5056134.285
      ],
      "aliases": [],
      "tempo_code": null,
      "itoa_code": null
    },
    "la_palma": {
      "clock_file": [],
      "apply_gps2utc": true,
      "timescale": "utc",
      "itrf_xyz": [
        5327021.651,
        -1719555.576,
        3051967.932
      ],
      "aliases": [
        "lap",
        "lapalma"
      ],
      "tempo_code": null,
      "itoa_code": null
    },
    "leap": {
      "clock_file": [
        "leap2effix.clk",
        "effix2gps.clk"
      ],
      "apply_gps2utc": true,
      "timescale": "utc",
      "itrf_xyz": [
        4033949.5,
        486989.4,
        4900430.8
      ],
      "aliases": [
        "leap"
      ],
      "tempo_code": null,
      "itoa_code": null
    },
    "lho": {
      "clock_file": [],
      "apply_gps2utc": true,
      "timescale": "utc",
      "itrf_xyz": [
        -2161414.9264,
        -3834695.1789,
        4600350.2266
      ],
      "aliases": [
        "h1",
        "hanford"
      ],
      "tempo_code": null,
      "itoa_code": null
    },
    "llo": {
      "clock_file": [],
      "apply_gps2utc": true,
      "timescale": "utc",
      "itrf_xyz": [
        -74276.0447,
        -5496283.7197,
        3224257.0174
      ],
      "aliases": [
        "l1",
        "livingston"
      ],
      "tempo_code": null,
      "itoa_code": null
    },
    "lofar": {
      "clock_file": [],
      "apply_gps2utc": true,
      "timescale": "utc",
      "itrf_xyz": [
        3826577.462,
        461022.624,
        5064892.526
      ],
      "aliases": [
        "lf",
        "t"
      ],
      "tempo_code": "t",
      "itoa_code": "lf"
    },
    "lst": {
      "clock_file": [],
      "apply_gps2utc": true,
      "timescale": "utc",
      "itrf_xyz": [
        5326832.7629,
        -1719636.1588,
        3051795.1913
      ],
      "aliases": [],
      "tempo_code": null,
      "itoa_code": null
    },
    "lwa1": {
      "clock_file": [],
      "apply_gps2utc": true,
      "timescale": "utc",
      "itrf_xyz": [
        -1602196.6,
        -5042313.47,
        3553971.51
      ],
      "aliases": [
        "x",
        "lw"
      ],
      "tempo_code": "x",
      "itoa_code": "lw"
    },
    "lwa_sv": {
      "clock_file": [],
      "apply_gps2utc": true,
      "timescale": "utc",
      "itrf_xyz": [
        -1531155.54418,
        -5045324.30517,
        3579583.8945
      ],
      "aliases": [
        "ls",
        "lwasv"
      ],
      "tempo_code": null,
      "itoa_code": "ls"
    },
    "magic": {
      "clock_file": [],
      "apply_gps2utc": true,
      "timescale": "utc",
      "itrf_xyz": [
        5326878.7967,
        -1719509.5201,
        3051884.5175
      ],
      "aliases": [],
      "tempo_code": null,
      "itoa_code": null
    },
    "meerkat": {
      "clock_file": [
        "mk2utc_observatory.clk"
      ],
      "apply_gps2utc": true,
      "timescale": "utc",
      "itrf_xyz": [
        5109360.133,
        2006852.586,
        -3238948.127
      ],
      "aliases": [
        "m",
        "mk"
      ],
      "tempo_code": "m",
      "itoa_code": "mk"
    },
    "mkiii": {
      "clock_file": [],
      "apply_gps2utc": true,
      "timescale": "utc",
      "itrf_xyz": [
        383395.727,
        -173759.585,
        5077751.313
      ],
      "aliases": [
        "jbmk3"
      ],
      "tempo_code": null,
      "itoa_code": null
    },
    "most": {
      "clock_file": [
        "mo2gps.clk"
      ],
      "apply_gps2utc": true,
      "timescale": "utc",
      "itrf_xyz": [
        -4483311.64,
        2648815.92,
        -3671909.31
      ],
      "aliases": [
        "mo",
        "e"
      ],
      "tempo_code": "e",
      "itoa_code": "mo"
    },
    "mwa": {
      "clock_file": [],
      "apply_gps2utc": true,
      "timescale": "utc",
      "itrf_xyz": [
        -2559454.08,
        5095372.14,
        -2849057.18
      ],
      "aliases": [
        "u",
        "mw"
      ],
      "tempo_code": "u",
      "itoa_code": "mw"
    },
    "nancay": {
      "clock_file": [],
      "apply_gps2utc": true,
      "timescale": "utc",
      "itrf_xyz": [
        4324165.81,
        165927.11,
        4670132.83
      ],
      "aliases": [
        "ncy",
        "f",
        "nc"
      ],
      "tempo_code": "f",
      "itoa_code": "nc"
    },
    "nanshan": {
      "clock_file": [],
      "apply_gps2utc": true,
      "timescale": "utc",
      "itrf_xyz": [
        228310.702,
        4631922.905,
        4367064.059
      ],
      "aliases": [
        "ns"
      ],
      "tempo_code": null,
      "itoa_code": null
    },
    "narrabri": {
      "clock_file": [],
      "apply_gps2utc": true,
      "timescale": "utc",
      "itrf_xyz": [
        -4752329.7,
        2790505.934,
        -3200483.747
      ],
      "aliases": [
        "atca"
      ],
      "tempo_code": null,
      "itoa_code": null
    },
    "ncyobs": {
      "clock_file": [
        "ncyobs2obspm.clk",
        "obspm2gps.clk"
      ],
      "apply_gps2utc": true,
      "timescale": "utc",
      "itrf_xyz": [
        4324165.81,
        165927.11,
        4670132.83
      ],
      "aliases": [
        "w",
        "nuppi"
      ],
      "tempo_code": null,
      "itoa_code": null
    },
    "nenufar": {
      "clock_file": [],
      "apply_gps2utc": true,
      "timescale": "utc",
      "itrf_xyz": [
        4323980.285,
        165608.799,
        4670302.65
      ],
      "aliases": [],
      "tempo_code": null,
      "itoa_code": null
    },
    "northern_cross": {
      "clock_file": [],
      "apply_gps2utc": true,
      "timescale": "utc",
      "itrf_xyz": [
        4461242.882451464,
        919559.8351226494,
        4449633.220012489
      ],
      "aliases": [
        "d",
        "bo"
      ],
      "tempo_code": "d",
      "itoa_code": "bo"
    },
    "op": {
      "clock_file": [],
      "apply_gps2utc": true,
      "timescale": "utc",
      "itrf_xyz": [
        4324165.81,
        165927.11,
        4670132.83
      ],
      "aliases": [
        "obspm"
      ],
      "tempo_code": null,
      "itoa_code": null
    },
    "ort": {
      "clock_file": [],
      "apply_gps2utc": true,
      "timescale": "utc",
      "itrf_xyz": [
        1442712.95,
        6087044.73,
        1251052.35
      ],
      "aliases": [
        "or"
      ],
      "tempo_code": null,
      "itoa_code": null
    },
    "parkes": {
      "clock_file": [
        "pks2gps.clk"
      ],
      "apply_gps2utc": true,
      "timescale": "utc",
      "itrf_xyz": [
        -4554231.5,
        2816759.1,
        -3454036.3
      ],
      "aliases": [
        "pk",
        "pks",
        "7"
      ],
      "tempo_code": "7",
      "itoa_code": "pk"
    },
    "pico_veleta": {
      "clock_file": [],
      "apply_gps2utc": true,
      "timescale": "utc",
      "itrf_xyz": [
        5088964.0,
        -301689.8,
        3825017.0
      ],
      "aliases": [
        "v",
        "pv"
      ],
      "tempo_code": "v",
      "itoa_code": "pv"
    },
    "princeton": {
      "clock_file": [],
      "apply_gps2utc": true,
      "timescale": "utc",
      "itrf_xyz": [
        1288748.38,
        -4694221.77,
        4107418.8
      ],
      "aliases": [
        "5",
        "pr"
      ],
      "tempo_code": "5",
      "itoa_code": "pr"
    },
    "ps1": {
      "clock_file": [],
      "apply_gps2utc": true,
      "timescale": "utc",
      "itrf_xyz": [
        -5461997.8,
        -2412559.0,
        2243024.0
      ],
      "aliases": [
        "p",
        "ps"
      ],
      "tempo_code": "p",
      "itoa_code": "ps"
    },
    "quabbin": {
      "clock_file": [],
      "apply_gps2utc": true,
      "timescale": "utc",
      "itrf_xyz": [
        1430913.3496148302,
        -4495711.383965823,
        4278113.974517222
      ],
      "aliases": [
        "2",
        "qu"
      ],
      "tempo_code": "2",
      "itoa_code": "qu"
    },
    "se607": {
      "clock_file": [],
      "apply_gps2utc": true,
      "timescale": "utc",
      "itrf_xyz": [
        3370272.092,
        712125.596,
        5349990.934
      ],
      "aliases": [
        "onlfr"
      ],
      "tempo_code": null,
      "itoa_code": null
    },
    "se607hba": {
      "clock_file": [],
      "apply_gps2utc": true,
      "timescale": "utc",
      "itrf_xyz": [
        3370272.092,
        712125.596,
        5349990.934
      ],
      "aliases": [
        "onlfrhba"
      ],
      "tempo_code": null,
      "itoa_code": null
    },
    "se607lba": {
      "clock_file": [],
      "apply_gps2utc": true,
      "timescale": "utc",
      "itrf_xyz": [
        3370287.366,
        712053.586,
        5349991.228
      ],
      "aliases": [
        "onlfrlba"
      ],
      "tempo_code": null,
      "itoa_code": null
    },
    "se607lbh": {
      "clock_file": [],
      "apply_gps2utc": true,
      "timescale": "utc",
      "itrf_xyz": [
        3370287.366,
        712053.586,
        5349991.228
      ],
      "aliases": [
        "onlfrlbh"
      ],
      "tempo_code": null,
      "itoa_code": null
    },
    "shao": {
      "clock_file": [],
      "apply_gps2utc": true,
      "timescale": "utc",
      "itrf_xyz": [
        -2826711.951,
        4679231.627,
        3274665.675
      ],
      "aliases": [
        "s",
        "sh"
      ],
      "tempo_code": "s",
      "itoa_code": "sh"
    },
    "srt": {
      "clock_file": [],
      "apply_gps2utc": true,
      "timescale": "utc",
      "itrf_xyz": [
        4865182.766,
        791922.689,
        4035137.174
      ],
      "aliases": [
        "sr",
        "z"
      ],
      "tempo_code": "z",
      "itoa_code": "sr"
    },
    "stl_geo": {
      "clock_file": [],
      "apply_gps2utc": false,
      "timescale": "utc",
      "itrf_xyz": null,
      "aliases": [
        "stl_geo",
        "spacecraft"
      ],
      "tempo_code": null,
      "itoa_code": null
    },
    "tabley": {
      "clock_file": [],
      "apply_gps2utc": true,
      "timescale": "utc",
      "itrf_xyz": [
        3817176.557,
        -162921.17,
        5089462.046
      ],
      "aliases": [
        "pickmere"
      ],
      "tempo_code": null,
      "itoa_code": null
    },
    "uao": {
      "clock_file": [],
      "apply_gps2utc": true,
      "timescale": "utc",
      "itrf_xyz": [
        228310.702,
        4631922.905,
        4367064.059
      ],
      "aliases": [
        "ns"
      ],
      "tempo_code": null,
      "itoa_code": null
    },
    "uk608": {
      "clock_file": [],
      "apply_gps2utc": true,
      "timescale": "utc",
      "itrf_xyz": [
        4008462.28,
        -100376.948,
        4943716.6
      ],
      "aliases": [
        "uklfr"
      ],
      "tempo_code": null,
      "itoa_code": null
    },
    "uk608hba": {
      "clock_file": [],
      "apply_gps2utc": true,
      "timescale": "utc",
      "itrf_xyz": [
        4008462.28,
        -100376.948,
        4943716.6
      ],
      "aliases": [
        "uklfrhba"
      ],
      "tempo_code": null,
      "itoa_code": null
    },
    "uk608lba": {
      "clock_file": [],
      "apply_gps2utc": true,
      "timescale": "utc",
      "itrf_xyz": [
        4008438.796,
        -100310.064,
        4943735.554
      ],
      "aliases": [
        "uklfrlba"
      ],
      "tempo_code": null,
      "itoa_code": null
    },
    "uk608lbh": {
      "clock_file": [],
      "apply_gps2utc": true,
      "timescale": "utc",
      "itrf_xyz": [
        4008438.796,
        -100310.064,
        4943735.554
      ],
      "aliases": [
        "uklfrlbh"
      ],
      "tempo_code": null,
      "itoa_code": null
    },
    "utr-2": {
      "clock_file": [],
      "apply_gps2utc": true,
      "timescale": "utc",
      "itrf_xyz": [
        3307865.236,
        2487350.541,
        4836939.784
      ],
      "aliases": [
        "utr2"
      ],
      "tempo_code": null,
      "itoa_code": null
    },
    "virgo": {
      "clock_file": [],
      "apply_gps2utc": true,
      "timescale": "utc",
      "itrf_xyz": [
        4546374.099,
        842989.6976,
        4378576.9624
      ],
      "aliases": [
        "v1"
      ],
      "tempo_code": null,
      "itoa_code": null
    },
    "vla": {
      "clock_file": [
        "time_vla.dat"
      ],
      "apply_gps2utc": true,
      "timescale": "utc",
      "itrf_xyz": [
        -1601192.0,
        -5041981.4,
        3554871.4
      ],
      "aliases": [
        "jvla",
        "6",
        "vl"
      ],
      "tempo_code": "6",
      "itoa_code": "vl"
    },
    "vla_site": {
      "clock_file": [],
      "apply_gps2utc": true,
      "timescale": "utc",
      "itrf_xyz": [
        -1601135.5133304405,
        -5042005.480977412,
        3554875.076856462
      ],
      "aliases": [
        "v2",
        "c"
      ],
      "tempo_code": "c",
      "itoa_code": "v2"
    },
    "warkworth_12m": {
      "clock_file": [],
      "apply_gps2utc": true,
      "timescale": "utc",
      "itrf_xyz": [
        -5115324.399,
        477843.305,
        -3767192.886
      ],
      "aliases": [
        "wark12m"
      ],
      "tempo_code": null,
      "itoa_code": null
    },
    "warkworth_30m": {
      "clock_file": [],
      "apply_gps2utc": true,
      "timescale": "utc",
      "itrf_xyz": [
        -5115425.6,
        477880.31,
        -3767042.81
      ],
      "aliases": [
        "wark30m"
      ],
      "tempo_code": null,
      "itoa_code": null
    },
    "wsrt": {
      "clock_file": [
        "wsrt2gps.clk"
      ],
      "apply_gps2utc": true,
      "timescale": "utc",
      "itrf_xyz": [
        3828445.659,
        445223.6,
        5064921.5677
      ],
      "aliases": [
        "we",
        "ws",
        "i"
      ],
      "tempo_code": "i",
      "itoa_code": "ws"
    }
  }
}
